rda_python_dscheck/PgCheck.py
rda_python_dscheck/__init__.py
rda_python_dscheck/ds_check.py
rda_python_dscheck/dscheck.py
rda_python_dscheck/dscheck.usg
rda_python_dscheck/pg_check.py
rda_python_dscheck-2.0.1.dist-info/licenses/LICENSE
rda_python_dscheck-2.0.1.dist-info/METADATA
rda_python_dscheck-2.0.1.dist-info/WHEEL
rda_python_dscheck-2.0.1.dist-info/entry_points.txt
rda_python_dscheck-2.0.1.dist-info/top_level.txt
rda_python_dscheck-2.0.1.dist-info/RECORD
